coremusic/__init__.py
coremusic/__init__.pyi
coremusic/__main__.py
coremusic/audio/__init__.py
coremusic/audio/_base.py
coremusic/audio/analysis.py
coremusic/audio/async_io.py
coremusic/audio/audiounit_host.py
coremusic/audio/buffer_pool.py
coremusic/audio/mmap_file.py
coremusic/audio/slicing.py
coremusic/audio/streaming.py
coremusic/audio/utilities.py
coremusic/audio/visualization.py
coremusic/buffer_utils.py
coremusic/capi.cpython-311-darwin.so
coremusic/capi.pyi
coremusic/cli/__init__.py
coremusic/cli/_formatters.py
coremusic/cli/_mappings.py
coremusic/cli/_utils.py
coremusic/cli/analyze.py
coremusic/cli/audio.py
coremusic/cli/completion.py
coremusic/cli/convert.py
coremusic/cli/devices.py
coremusic/cli/main.py
coremusic/cli/midi.py
coremusic/cli/plugins.py
coremusic/cli/sequence.py
coremusic/constants.py
coremusic/link.cpython-311-darwin.so
coremusic/log.py
coremusic/midi/__init__.py
coremusic/midi/link.py
coremusic/midi/transform.py
coremusic/midi/utilities.py
coremusic/music/__init__.py
coremusic/music/theory.py
coremusic/objects/__init__.py
coremusic/objects/audio.py
coremusic/objects/audiounit.py
coremusic/objects/augraph.py
coremusic/objects/base.py
coremusic/objects/clock.py
coremusic/objects/devices.py
coremusic/objects/exceptions.py
coremusic/objects/midi.py
coremusic/objects/music.py
coremusic/objects.pyi
coremusic/os_status.py
coremusic/py.typed
coremusic/shortcuts.py
coremusic/utils/__init__.py
coremusic/utils/batch.py
coremusic/utils/fourcc.py
coremusic/utils/scipy.py
coremusic-0.1.13.dist-info/METADATA
coremusic-0.1.13.dist-info/WHEEL
coremusic-0.1.13.dist-info/entry_points.txt
coremusic-0.1.13.dist-info/licenses/LICENSE
coremusic-0.1.13.dist-info/RECORD
