Metadata-Version: 2.4
Name: coremusic
Version: 0.1.13
Summary: Python bindings for Apple CoreAudio
Author-Email: Shakeeb Alireza <shakfu@users.noreply.github.com>
License-Expression: MIT
License-File: LICENSE
Classifier: Development Status :: 4 - Beta
Classifier: Intended Audience :: Developers
Classifier: Intended Audience :: Science/Research
Classifier: Operating System :: MacOS :: MacOS X
Classifier: Programming Language :: Python :: 3
Classifier: Programming Language :: Python :: 3.11
Classifier: Programming Language :: Python :: 3.12
Classifier: Programming Language :: Python :: 3.13
Classifier: Programming Language :: Python :: 3.14
Classifier: Programming Language :: Python :: Implementation :: CPython
Classifier: Programming Language :: Cython
Classifier: Topic :: Multimedia :: Sound/Audio
Classifier: Topic :: Multimedia :: Sound/Audio :: Analysis
Classifier: Topic :: Multimedia :: Sound/Audio :: Capture/Recording
Classifier: Topic :: Multimedia :: Sound/Audio :: MIDI
Classifier: Topic :: Multimedia :: Sound/Audio :: Players
Classifier: Topic :: Software Development :: Libraries :: Python Modules
Classifier: Typing :: Typed
Project-URL: Homepage, https://github.com/shakfu/coremusic
Project-URL: Issues, https://github.com/shakfu/coremusic/issues
Requires-Python: >=3.11
Provides-Extra: analysis
Requires-Dist: numpy>=2.0; extra == "analysis"
Requires-Dist: scipy>=1.10; extra == "analysis"
Provides-Extra: visualization
Requires-Dist: matplotlib>=3.8; extra == "visualization"
Provides-Extra: all
Requires-Dist: numpy>=2.0; extra == "all"
Requires-Dist: scipy>=1.10; extra == "all"
Requires-Dist: matplotlib>=3.8; extra == "all"
